MengJinhuaYujiazhiWanchengVol1/Dockerfile
MengJinhuaYujiazhiWanchengVol1/README.md
MengJinhuaYujiazhiWanchengVol1/__init__.py
MengJinhuaYujiazhiWanchengVol1/__main__.py
MengJinhuaYujiazhiWanchengVol1/file.epub
MengJinhuaYujiazhiWanchengVol1/index.html
MengJinhuaYujiazhiWanchengVol1/css/__init__.py
MengJinhuaYujiazhiWanchengVol1/css/annotations.css
MengJinhuaYujiazhiWanchengVol1/css/main.css
MengJinhuaYujiazhiWanchengVol1/css/normalize.css
MengJinhuaYujiazhiWanchengVol1/css/popup.css
MengJinhuaYujiazhiWanchengVol1/font/__init__.py
MengJinhuaYujiazhiWanchengVol1/font/fontello.eot
MengJinhuaYujiazhiWanchengVol1/font/fontello.svg
MengJinhuaYujiazhiWanchengVol1/font/fontello.ttf
MengJinhuaYujiazhiWanchengVol1/font/fontello.woff
MengJinhuaYujiazhiWanchengVol1/img/__init__.py
MengJinhuaYujiazhiWanchengVol1/img/annotator-glyph-sprite.png
MengJinhuaYujiazhiWanchengVol1/img/annotator-icon-sprite.png
MengJinhuaYujiazhiWanchengVol1/img/apple-touch-icon.png
MengJinhuaYujiazhiWanchengVol1/img/cancelfullscreen.png
MengJinhuaYujiazhiWanchengVol1/img/close.png
MengJinhuaYujiazhiWanchengVol1/img/fullscreen.png
MengJinhuaYujiazhiWanchengVol1/img/loader.gif
MengJinhuaYujiazhiWanchengVol1/img/menu-icon.png
MengJinhuaYujiazhiWanchengVol1/img/save.png
MengJinhuaYujiazhiWanchengVol1/img/saved.png
MengJinhuaYujiazhiWanchengVol1/img/settings-s.png
MengJinhuaYujiazhiWanchengVol1/img/settings.png
MengJinhuaYujiazhiWanchengVol1/img/star.png
MengJinhuaYujiazhiWanchengVol1/js/__init__.py
MengJinhuaYujiazhiWanchengVol1/js/epub.js
MengJinhuaYujiazhiWanchengVol1/js/epub.min.js
MengJinhuaYujiazhiWanchengVol1/js/epub.min.map
MengJinhuaYujiazhiWanchengVol1/js/hooks.min.js
MengJinhuaYujiazhiWanchengVol1/js/hooks.min.map
MengJinhuaYujiazhiWanchengVol1/js/reader.js
MengJinhuaYujiazhiWanchengVol1/js/reader.js.map
MengJinhuaYujiazhiWanchengVol1/js/reader.min.js
MengJinhuaYujiazhiWanchengVol1/js/reader.min.map
MengJinhuaYujiazhiWanchengVol1/js/hooks/__init__.py
meng_jinhua_yujiazhi_wancheng_vol1-2022.10.9.1.dist-info/METADATA
meng_jinhua_yujiazhi_wancheng_vol1-2022.10.9.1.dist-info/WHEEL
meng_jinhua_yujiazhi_wancheng_vol1-2022.10.9.1.dist-info/entry_points.txt
meng_jinhua_yujiazhi_wancheng_vol1-2022.10.9.1.dist-info/top_level.txt
meng_jinhua_yujiazhi_wancheng_vol1-2022.10.9.1.dist-info/RECORD
